subto/__init__.py
subto/__version__.py
subto/job.py
subto/utils.py
subto-0.1.2.dist-info/METADATA
subto-0.1.2.dist-info/WHEEL
subto-0.1.2.dist-info/entry_points.txt
subto-0.1.2.dist-info/top_level.txt
subto-0.1.2.dist-info/RECORD
