Metadata-Version: 2.1
Name: subto
Version: 0.1.2
Summary: A package to make life easier when submitting jobs to schedulers
Home-page: https://gitlab.com/kragskow-group/subto
Author: Jon Kragskow
Author-email: jgck20@bath.ac.uk
Project-URL: Bug Tracker, https://gitlab.com/kragskow-group/subto/issues
Project-URL: Documentation, https://www.kragskow.dev/subto/index.html
Classifier: Programming Language :: Python :: 3
Classifier: License :: OSI Approved :: GNU General Public License v3 (GPLv3)
Classifier: Operating System :: OS Independent
Requires-Python: >=3.12
Requires-Dist: xyz-py >=5.13.0
